pauc/__init__.py
pauc/plot.py
pauc/roc_core.py
pauc/smoothing.py
pauc/stats.py
pauc-0.2.1.dist-info/licenses/LICENSE
pauc-0.2.1.dist-info/METADATA
pauc-0.2.1.dist-info/WHEEL
pauc-0.2.1.dist-info/top_level.txt
pauc-0.2.1.dist-info/RECORD
